depz/__init__.py
depz/__main__.py
depz/x00_common.py
depz/x00_version.py
depz/x01_testsBase.py
depz/x50_resolve.py
depz/x50_unlink.py
depz/x80_rescanRelink.py
depz/x98_dooo.py
depz/x99_run.py
depz/x99_run_test.py
depz-0.0.6.1.dist-info/LICENSE.txt
depz-0.0.6.1.dist-info/METADATA
depz-0.0.6.1.dist-info/WHEEL
depz-0.0.6.1.dist-info/entry_points.txt
depz-0.0.6.1.dist-info/top_level.txt
depz-0.0.6.1.dist-info/RECORD
