Metadata-Version: 2.1
Name: depz
Version: 0.0.6.1
Summary: Command line tool for symlinking directories with reusable code into the project
Home-page: https://github.com/rtmigo/depz
Author: Art Galkin
Author-email: ortemeo@gmail.com
License: BSD-3-Clause
Keywords: files,package,library,programming,local,project,symlink,dependencies,directories,library-management,package-management,source-code,reusable-code
Platform: UNKNOWN
Classifier: Development Status :: 3 - Alpha
Classifier: Intended Audience :: Developers
Classifier: License :: OSI Approved :: BSD License
Classifier: Programming Language :: Python :: 3.7
Classifier: Programming Language :: Python :: 3.8
Classifier: Programming Language :: Python :: 3.9
Classifier: Typing :: Typed
Classifier: Topic :: Software Development :: Build Tools
Classifier: Operating System :: POSIX
